{
    "items": [
        {
          "name": "The Avengers - I am Always Angry - Hulk SMASH Scene",
          "url": "https://www.youtube.com/watch?v=udKE1ksKWDE",
          "thumbnail": "https://i.ytimg.com/vi/udKE1ksKWDE/maxresdefault.jpg",
          "type": "video"
        },
        {
          "name": "Thor vs Star-Lord Scene - Quill Making His Voice Deeper - Avengers: Infinity War (2018) ",
          "url": "https://www.youtube.com/watch?v=It67i5uKqos",
          "thumbnail": "https://i.ytimg.com/vi/It67i5uKqos/maxresdefault.jpg",
          "type": "video"
        },
        {
          "name": "You Know How Much I Sacrificed? - Spider-Man (2002)",
          "url": "https://www.youtube.com/watch?v=jca4TchXelE",
          "thumbnail": "https://i.ytimg.com/vi/jca4TchXelE/maxresdefault.jpg",
          "type": "video"
        },
        {
          "type": "message"
        }
    ]
}
